inline_example/__init__.py
inline_example/examples/example1.py
inline_example/main.py
inline_example/template.py
inline_example-0.1.3.dist-info/WHEEL
inline_example-0.1.3.dist-info/METADATA
inline_example-0.1.3.dist-info/RECORD
