Metadata-Version: 2.1
Name: inline-example
Version: 0.1.3
Summary: 
Author: MBeebe
Author-email: pyn-sol@beebe.dev
Requires-Python: >=3.8,<4.0
Classifier: Programming Language :: Python :: 3
Classifier: Programming Language :: Python :: 3.10
Classifier: Programming Language :: Python :: 3.8
Classifier: Programming Language :: Python :: 3.9
